Workbook
Name aporte: App!$C$14
Name patrimonio: App!$C$17
Name qtd_anos: App!$C$15
Name rendimento_carteira: App!$C$10
Name salario: App!$C$9
Name sugestao_investimento: App!$C$11
Name taxa_mensal: App!$C$16

Sheet App
B8: CONFIGURAÇÕES
B9: Salário | C9: 2000
B10: Rendimentos Carteira | C10: 0.006
B11: Sugestão de Investimento | C11: =C9*30% -> 600
B13: INVESTIMENTO MENSAL
B14: Quanto investir por mês? | C14: 200
B15: Por quantos anos? | C15: 5
B16: Taxa de rendimento mensal? | C16: 0.01079
B17: Patrimônio acumulado? | C17: =FV(taxa_mensal, (qtd_anos*12), aporte)*-1 -> 16755.383
B18: Dividendos Mensais? | C18: =patrimonio*rendimento_carteira -> 100.5323
B20: Cenários | D20: Dividendos
A21: 2 | B21: Quanto em 2 anos? | C21: =FV($C$16, $A21*12,$C$14*-1) -> 5445.5255 | D21: =C21*rendimento_carteira -> 32.673153
A22: 5 | B22: Quanto em 5 anos? | C22: =FV($C$16, $A22*12,$C$14*-1) -> 16755.383 | D22: =C22*rendimento_carteira -> 100.5323
A23: 10 | B23: Quanto em 10 anos? | C23: =FV($C$16, $A23*12,$C$14*-1) -> 48656.843 | D23: =C23*rendimento_carteira -> 291.94106
A24: 20 | B24: Quanto em 20 anos? | C24: =FV($C$16, $A24*12,$C$14*-1) -> 225039.68 | D24: =C24*rendimento_carteira -> 1350.2381
A25: 30 | B25: Quanto em 30 anos? | C25: =FV($C$16, $A25*12,$C$14*-1) -> 864433.93 | D25: =C25*rendimento_carteira -> 5186.6036
B30: PERFIL | C30: Agressivo
B31: VALOR A SER INVESTIDO POR MÊS | C31: =aporte -> 200
B34: TIPO DE FII | C34: Percentual Sugerido | D34: Valor
B35: PAPEL | C35: =VLOOKUP($C$30&"-"&B35,Apoio!$A:$D,4,0) -> 0.5 | D35: =C35*$C$31 -> 100
B36: TIJOLO | C36: =VLOOKUP($C$30&"-"&B36,Apoio!$A:$D,4,0) -> 0.1 | D36: =C36*$C$31 -> 20
B37: HIBRÍDOS | C37: =VLOOKUP($C$30&"-"&B37,Apoio!$A:$D,4,0) -> 0.05 | D37: =C37*$C$31 -> 10
B38: FOFs | C38: =VLOOKUP($C$30&"-"&B38,Apoio!$A:$D,4,0) -> 0.05 | D38: =C38*$C$31 -> 10
B39: DESENVOLVIMENTO | C39: =VLOOKUP($C$30&"-"&B39,Apoio!$A:$D,4,0) -> 0.2 | D39: =C39*$C$31 -> 40
B40: HOTELARIAS | C40: =VLOOKUP($C$30&"-"&B40,Apoio!$A:$D,4,0) -> 0.1 | D40: =C40*$C$31 -> 20
D41: =SUM(D35:D40) -> 200

Sheet Apoio
A2: CHAVE | B2: PERFIL | C2: TIPO DE FII | D2: %
A3: =B3&"-"&C3 -> Conservador-PAPEL | B3: Conservador | C3: PAPEL | D3: 0.3
A4: =B4&"-"&C4 -> Conservador-TIJOLO | B4: Conservador | C4: TIJOLO | D4: 0.5 | G4: =A10 -> Moderado-TIJOLO | H4: =VLOOKUP(G4,$A:$D,4,0) -> 0.35
A5: =B5&"-"&C5 -> Conservador-HIBRÍDOS | B5: Conservador | C5: HIBRÍDOS | D5: 0.1
A6: =B6&"-"&C6 -> Conservador-FOFs | B6: Conservador | C6: FOFs | D6: 0.1
A7: =B7&"-"&C7 -> Conservador-DESENVOLVIMENTO | B7: Conservador | C7: DESENVOLVIMENTO | D7: 0
A8: =B8&"-"&C8 -> Conservador-HOTELARIAS | B8: Conservador | C8: HOTELARIAS | D8: 0
A9: =B9&"-"&C9 -> Moderado-PAPEL | B9: Moderado | C9: PAPEL | D9: 0.32
A10: =B10&"-"&C10 -> Moderado-TIJOLO | B10: Moderado | C10: TIJOLO | D10: 0.35
A11: =B11&"-"&C11 -> Moderado-HIBRÍDOS | B11: Moderado | C11: HIBRÍDOS | D11: 0.08
A12: =B12&"-"&C12 -> Moderado-FOFs | B12: Moderado | C12: FOFs | D12: 0.05
A13: =B13&"-"&C13 -> Moderado-DESENVOLVIMENTO | B13: Moderado | C13: DESENVOLVIMENTO | D13: 0.1
A14: =B14&"-"&C14 -> Moderado-HOTELARIAS | B14: Moderado | C14: HOTELARIAS | D14: 0.1
A15: =B15&"-"&C15 -> Agressivo-PAPEL | B15: Agressivo | C15: PAPEL | D15: 0.5
A16: =B16&"-"&C16 -> Agressivo-TIJOLO | B16: Agressivo | C16: TIJOLO | D16: 0.1
... A20: =B20&"-"&C20 -> Agressivo-HOTELARIAS | B20: Agressivo | C20: HOTELARIAS | D20: 0.1
